[
  {
    "id": "1",
    "residentName": "Roberto Cruz",
    "address": "Block 5, Lot 12, Phase 2",
    "contactNumber": "09171234567",
    "emergencyContact": "09189876543",
    "householdCount": 5,
    "notes": "Has elderly member requiring assistance",
    "status": "active",
    "createdAt": "2026-02-10T14:20:00Z",
    "updatedAt": "2026-02-10T14:20:00Z"
  },
  {
    "id": "2",
    "residentName": "Angela Fernandez",
    "address": "Block 3, Lot 8, Phase 1",
    "contactNumber": "09267891234",
    "emergencyContact": "09171112233",
    "householdCount": 4,
    "notes": "Medical equipment on-site",
    "status": "active",
    "createdAt": "2026-02-12T11:45:00Z",
    "updatedAt": "2026-02-12T11:45:00Z"
  },
  {
    "id": "3",
    "residentName": "Carlos Mendoza",
    "address": "Block 7, Lot 15, Phase 3",
    "contactNumber": "09351234567",
    "emergencyContact": "09189998877",
    "householdCount": 6,
    "notes": "Three young children",
    "status": "active",
    "createdAt": "2026-02-15T09:30:00Z",
    "updatedAt": "2026-02-15T09:30:00Z"
  },
  {
    "id": "4",
    "residentName": "Luz Garcia",
    "address": "Block 2, Lot 5, Phase 1",
    "contactNumber": "09177654321",
    "emergencyContact": "09265554444",
    "householdCount": 3,
    "notes": "",
    "status": "active",
    "createdAt": "2026-02-18T16:00:00Z",
    "updatedAt": "2026-02-18T16:00:00Z"
  },
  {
    "id": "5",
    "residentName": "Eduardo Santos",
    "address": "Block 6, Lot 22, Phase 2",
    "contactNumber": "09281112222",
    "emergencyContact": "09173334444",
    "householdCount": 7,
    "notes": "Two-story house, difficult evacuation access",
    "status": "active",
    "createdAt": "2026-02-20T13:15:00Z",
    "updatedAt": "2026-02-20T13:15:00Z"
  }
]
